embodier/__init__.py
embodier/__main__.py
embodier-1.0.9.dist-info/LICENCE
embodier-1.0.9.dist-info/METADATA
embodier-1.0.9.dist-info/WHEEL
embodier-1.0.9.dist-info/entry_points.txt
embodier-1.0.9.dist-info/top_level.txt
embodier-1.0.9.dist-info/RECORD
