Metadata-Version: 2.1
Name: embodier
Version: 1.0.9
Summary: Embodier creates a unique avatar that provide you image as a PNG, JPG, or Base64 string. This package is used to provide an avatar for new users on your application.
Home-page: https://github.com/2000prath/embodier
Author: Prathamesh Patkar
Author-email: 2000prath@gmail.com
License: MIT
Project-URL: Source Code, https://github.com/2000prath/embodier
Project-URL: API Reference, https://embodierapi.herokuapp.com/
Platform: UNKNOWN
Classifier: License :: OSI Approved :: MIT License
Classifier: Programming Language :: Python :: 3.6
Classifier: Programming Language :: Python :: 3.7
Classifier: Programming Language :: Python :: 3.8
License-File: LICENCE
Requires-Dist: numpy (==1.19.5)
Requires-Dist: Pillow (==8.1.0)
